pish/__init__.py
pish-0.5.dist-info/METADATA
pish-0.5.dist-info/WHEEL
pish-0.5.dist-info/entry_points.txt
pish-0.5.dist-info/top_level.txt
pish-0.5.dist-info/RECORD
