Metadata-Version: 2.1
Name: pish
Version: 0.5
Summary: Versatile tools for connecting to ssh, local shell, and/or su(do) in order to execute shell commands there, to manage ssh identity and host keys, and more.
Home-page: UNKNOWN
Author: pino
Author-email: ale@ginger.ws
License: GPL-3
Keywords: ssh shell key management
Platform: UNKNOWN
Classifier: Programming Language :: Python :: 3.4
